LICENSE
MANIFEST.in
README.rst
docker_command.py
setup.py
topology.py
yans.py
YANS.egg-info/SOURCES.txt
yans.egg-info/PKG-INFO
yans.egg-info/SOURCES.txt
yans.egg-info/dependency_links.txt
yans.egg-info/entry_points.txt
yans.egg-info/not-zip-safe
yans.egg-info/requires.txt
yans.egg-info/top_level.txt