Metadata-Version: 1.1
Name: YANS
Version: 0.2.3
Summary: Yet Another Network Simulator
Home-page: https://github.com/kennethjiang/YANS
Author: Kenneth Jiang
Author-email: kenneth.jiang@gmail.com
License: Copyright 2017 Kenneth Jiang
